{
  "parent": "minecraft:recipes/root",
  "rewards": {
    "recipes": [
      "fairyfactions:fairy_wand"
    ]
  },
  "criteria": {
    "has_stick": {
      "trigger": "minecraft:inventory_changed",
      "conditions": {
        "items": [
          {
            "items": [
              "minecraft:stick"
            ]
          }
        ]
      }
    },
    "has_the_recipe": {
      "trigger": "minecraft:recipe_unlocked",
      "conditions": {
        "recipe": "fairyfactions:fairy_wand"
      }
    }
  },
  "requirements": [
    [
      "has_stick",
      "has_the_recipe"
    ]
  ]
}